<math xmlns="http://www.w3.org/1998/Math/MathML"><mi>C</mi><msub><mi>r</mi><mn>2</mn></msub><msup><msub><mi>O</mi><mn>7</mn></msub><mrow><mn>2</mn><mo>-</mo></mrow></msup><mo>&nbsp;</mo><mo>+</mo><mo>&nbsp;</mo><mi>X</mi><mo>&nbsp;</mo><mo>&#8594;</mo><mo>&nbsp;</mo><mi>C</mi><msup><mi>r</mi><mrow><mn>3</mn><mo>+</mo></mrow></msup><mo>&nbsp;</mo><mo>+</mo><mo>&nbsp;</mo><msub><mi>H</mi><mn>2</mn></msub><mi>O</mi><mo>&nbsp;</mo><mo>+</mo><mo>&nbsp;</mo><mi>O</mi><mi>x</mi><mi>i</mi><mi>d</mi><mi>i</mi><mi>s</mi><mi>e</mi><mi>d</mi><mo>&nbsp;</mo></math>


true







