<math xmlns="http://www.w3.org/1998/Math/MathML"><mi>D</mi><mo>=</mo><mfenced close="|" open="|"><mtable><mtr><mtd><mn>1</mn></mtd><mtd><mn>1</mn></mtd><mtd><mn>1</mn></mtd></mtr><mtr><mtd><mn>1</mn></mtd><mtd><mn>1</mn><mo>+</mo><mi>x</mi></mtd><mtd><mn>1</mn></mtd></mtr><mtr><mtd><mn>1</mn></mtd><mtd><mn>1</mn></mtd><mtd><mn>1</mn><mo>+</mo><mi>y</mi></mtd></mtr></mtable></mfenced><mo>&nbsp;</mo><mi>f</mi><mi>o</mi><mi>r</mi><mo>&nbsp;</mo><mi>x</mi><mo>&#8800;</mo><mn>0</mn><mo>,</mo><mi>y</mi><mo>&#8800;</mo><mn>0</mn><mo>,</mo><mo>&nbsp;</mo><mi>t</mi><mi>h</mi><mi>e</mi><mi>n</mi><mo>&nbsp;</mo><mi>D</mi><mo>&nbsp;</mo><mi>i</mi><mi>s</mi></math>


true







