<math xmlns="http://www.w3.org/1998/Math/MathML"><mi mathvariant="normal">cos</mi><mi>&#920;</mi><mfenced close="]" open="["><mtable><mtr><mtd><mi mathvariant="normal">cos</mi><mi>&#920;</mi></mtd><mtd><mi mathvariant="normal">sin</mi><mi>&#920;</mi></mtd></mtr><mtr><mtd><mi mathvariant="normal">sin</mi><mi>&#920;</mi></mtd><mtd><mi mathvariant="normal">cos</mi><mi>&#920;</mi></mtd></mtr></mtable></mfenced><mo>+</mo><mi mathvariant="normal">sin</mi><mi>&#920;</mi><mfenced close="]" open="["><mtable><mtr><mtd><mi mathvariant="normal">sin</mi><mi>&#920;</mi></mtd><mtd><mo>-</mo><mi mathvariant="normal">cos</mi><mi>&#920;</mi></mtd></mtr><mtr><mtd><mi mathvariant="normal">cos</mi><mi>&#920;</mi></mtd><mtd><mo>&nbsp;</mo><mo>&nbsp;</mo><mi mathvariant="normal">sin</mi><mi>&#920;</mi></mtd></mtr></mtable></mfenced><mo>&nbsp;</mo><mi>i</mi><mi>s</mi><mo>&nbsp;</mo><mi>e</mi><mi>q</mi><mi>u</mi><mi>a</mi><mi>l</mi><mo>&nbsp;</mo><mi>t</mi><mi>o</mi></math>


true







