<math xmlns="http://www.w3.org/1998/Math/MathML"><mfenced close="|" open="|"><mtable><mtr><mtd><mi mathvariant="normal">cos</mi><mn>2</mn><mi>&#952;</mi></mtd><mtd><msup><mi mathvariant="normal">sin</mi><mn>2</mn></msup><mi>&#952;</mi></mtd><mtd><mi mathvariant="normal">cos</mi><mn>4</mn><mi>&#952;</mi></mtd></mtr><mtr><mtd><msup><mi mathvariant="normal">sin</mi><mn>2</mn></msup><mi>&#952;</mi></mtd><mtd><mi mathvariant="normal">cos</mi><mn>2</mn><mi>&#952;</mi></mtd><mtd><msup><mi mathvariant="normal">cos</mi><mn>2</mn></msup><mi>&#952;</mi></mtd></mtr><mtr><mtd><mi mathvariant="normal">cos</mi><mn>4</mn><mi>&#952;</mi></mtd><mtd><msup><mi mathvariant="normal">cos</mi><mn>2</mn></msup><mi>&#952;</mi></mtd><mtd><mi mathvariant="normal">cos</mi><mn>2</mn><mi>&#952;</mi></mtd></mtr></mtable></mfenced></math>


true







